dbgpt_hub/__init__.py
dbgpt_hub/baseline/__init__.py
dbgpt_hub/baseline/baseline.json
dbgpt_hub/baseline/show_result.py
dbgpt_hub/baseline/show_result_api.py
dbgpt_hub/configs/__init__.py
dbgpt_hub/configs/config.py
dbgpt_hub/configs/data_args.py
dbgpt_hub/configs/ds_config.json
dbgpt_hub/configs/ds_config_stage3.json
dbgpt_hub/configs/model_args.py
dbgpt_hub/data/dataset_info.json
dbgpt_hub/data/eval_data/20k.pkl
dbgpt_hub/data/eval_data/dev.json
dbgpt_hub/data/eval_data/dev_sql.json
dbgpt_hub/data/eval_data/download-db-files-README.txt
dbgpt_hub/data/eval_data/gold.txt
dbgpt_hub/data/eval_data/gold_natsql2sql.txt
dbgpt_hub/data/eval_data/tables.json
dbgpt_hub/data/eval_data/tables_for_natsql.json
dbgpt_hub/data/example_text2sql.json
dbgpt_hub/data_process/__init__.py
dbgpt_hub/data_process/connectors/__init__.py
dbgpt_hub/data_process/connectors/anydb_connector.py
dbgpt_hub/data_process/connectors/base_connector.py
dbgpt_hub/data_process/connectors/mysql_connector.py
dbgpt_hub/data_process/data_utils.py
dbgpt_hub/data_process/sft_dataset.py
dbgpt_hub/data_process/specialized_scenario_data_processing.py
dbgpt_hub/data_process/sql_data_process.py
dbgpt_hub/data_process/sql_data_process_api.py
dbgpt_hub/data_process/table_meta_data_processor.py
dbgpt_hub/dataset_util/__init__.py
dbgpt_hub/dataset_util/db_config.yaml
dbgpt_hub/dataset_util/main.py
dbgpt_hub/eval/__init__.py
dbgpt_hub/eval/evaluation.py
dbgpt_hub/eval/evaluation_api.py
dbgpt_hub/eval/exec_eval.py
dbgpt_hub/eval/parse.py
dbgpt_hub/eval/process_sql.py
dbgpt_hub/llm_base/__init__.py
dbgpt_hub/llm_base/adapter.py
dbgpt_hub/llm_base/chat_model.py
dbgpt_hub/llm_base/config_parser.py
dbgpt_hub/llm_base/load_tokenizer.py
dbgpt_hub/llm_base/loggings.py
dbgpt_hub/llm_base/model_trainer.py
dbgpt_hub/output/adapter/.gitkeep
dbgpt_hub/output/logs/.gitkeep
dbgpt_hub/output/pred/.gitkeep
dbgpt_hub/predict/__init__.py
dbgpt_hub/predict/predict.py
dbgpt_hub/predict/predict_api.py
dbgpt_hub/scripts/export_merge.sh
dbgpt_hub-0.3.1.dist-info/LICENSE
dbgpt_hub-0.3.1.dist-info/METADATA
dbgpt_hub-0.3.1.dist-info/WHEEL
dbgpt_hub-0.3.1.dist-info/RECORD
