Metadata-Version: 2.1
Name: dbgpt_hub
Version: 0.3.1
Summary: DB-GPT-Hub: Text-to-SQL parsing with LLMs
License: MIT
Author: Your Name
Author-email: you@example.com
Requires-Python: >=3.10,<3.13
Classifier: License :: OSI Approved :: MIT License
Classifier: Programming Language :: Python :: 3
Classifier: Programming Language :: Python :: 3.10
Classifier: Programming Language :: Python :: 3.11
Requires-Dist: accelerate (==0.21.0)
Requires-Dist: bitsandbytes (==0.41.2)
Requires-Dist: black (>=23.11.0,<24.0.0)
Requires-Dist: datasets (>=2.12.0)
Requires-Dist: deepspeed (==0.10.2)
Requires-Dist: docopt (>=0.6.2,<0.7.0)
Requires-Dist: einops (==0.6.1)
Requires-Dist: evaluate (==0.4.0)
Requires-Dist: fastapi (==0.95.1)
Requires-Dist: func-timeout (==4.3.5)
Requires-Dist: gradio (>=3.36.0)
Requires-Dist: jieba (>=0.42.1,<0.43.0)
Requires-Dist: jsonlines (>=4.0.0,<5.0.0)
Requires-Dist: markupsafe (==2.1.3)
Requires-Dist: matplotlib (>=3.8.1,<4.0.0)
Requires-Dist: nltk (>=3.8.1,<4.0.0)
Requires-Dist: nvidia-cublas-cu12 (==12.1.3.1)
Requires-Dist: nvidia-cuda-cupti-cu12 (==12.1.105)
Requires-Dist: nvidia-cuda-nvrtc-cu12 (==12.1.105)
Requires-Dist: nvidia-cuda-runtime-cu12 (==12.1.105)
Requires-Dist: nvidia-cudnn-cu12 (==8.9.2.26)
Requires-Dist: nvidia-cufft-cu12 (==11.0.2.54)
Requires-Dist: nvidia-curand-cu12 (==10.3.2.106)
Requires-Dist: nvidia-cusolver-cu12 (==11.4.5.107)
Requires-Dist: nvidia-cusparse-cu12 (==12.1.0.106)
Requires-Dist: nvidia-nccl-cu12 (==2.18.1)
Requires-Dist: nvidia-nvjitlink-cu12 (>=12.3.52,<13.0.0)
Requires-Dist: nvidia-nvtx-cu12 (==12.1.105)
Requires-Dist: peft (==0.4.0)
Requires-Dist: prettytable (>=3.9.0,<4.0.0)
Requires-Dist: pydantic (==1.10.11)
Requires-Dist: pylint (>=3.0.2,<4.0.0)
Requires-Dist: pymysql (==1.1.0)
Requires-Dist: pyright (>=1.1.335,<2.0.0)
Requires-Dist: pyyaml (==6.0.1)
Requires-Dist: rapidfuzz (>=3.5.2,<4.0.0)
Requires-Dist: rouge-chinese (>=1.0.3,<2.0.0)
Requires-Dist: scikit-learn (==1.2.2)
Requires-Dist: scipy (>=1.11.3,<2.0.0)
Requires-Dist: sentencepiece (==0.1.99)
Requires-Dist: sqlparse (>=0.4.4,<0.5.0)
Requires-Dist: sse-starlette (>=1.6.5,<2.0.0)
Requires-Dist: tiktoken (>=0.5.1,<0.6.0)
Requires-Dist: torch (>=2.0.0,<3.0.0)
Requires-Dist: transformers (==4.33.2)
Requires-Dist: transformers-stream-generator (>=0.0.4,<0.0.5)
Requires-Dist: triton (==2.1.0)
Requires-Dist: trl (>=0.5.0)
Requires-Dist: uvicorn (>=0.24.0.post1,<0.25.0)
Requires-Dist: uvicorn-http2 (>=0.0.0,<0.0.1)
Requires-Dist: wandb (==0.15.3)
